{"month_page_array":[{"month_page_keys":"https:\/\/essentialoilwizardry.com\/","month_page_clicks":725,"month_page_impressions":15183},{"month_page_keys":"https:\/\/essentialoilwizardry.com\/product\/blue-lotus-absolute\/","month_page_clicks":190,"month_page_impressions":7273},{"month_page_keys":"https:\/\/essentialoilwizardry.com\/essential-oils\/","month_page_clicks":49,"month_page_impressions":1173},{"month_page_keys":"https:\/\/essentialoilwizardry.com\/product\/mugwort-essential-oil\/","month_page_clicks":37,"month_page_impressions":2132},{"month_page_keys":"https:\/\/essentialoilwizardry.com\/product\/tobacco-absolute\/","month_page_clicks":34,"month_page_impressions":1744},{"month_page_keys":"https:\/\/essentialoilwizardry.com\/product\/dragons-blood-sangre-de-grado\/","month_page_clicks":29,"month_page_impressions":1681},{"month_page_keys":"https:\/\/essentialoilwizardry.com\/product\/kava-extract-co2\/","month_page_clicks":28,"month_page_impressions":1468},{"month_page_keys":"https:\/\/essentialoilwizardry.com\/product\/trinity-blend\/","month_page_clicks":24,"month_page_impressions":1016},{"month_page_keys":"https:\/\/essentialoilwizardry.com\/product\/calea-z-aztec-dream-herb\/","month_page_clicks":23,"month_page_impressions":2002},{"month_page_keys":"https:\/\/essentialoilwizardry.com\/product\/zanthoxylum-essential-oil\/","month_page_clicks":22,"month_page_impressions":272}],"three_page_array":[{"three_page_keys":"https:\/\/essentialoilwizardry.com\/","three_page_clicks":1818,"three_page_impressions":54059},{"three_page_keys":"https:\/\/essentialoilwizardry.com\/product\/blue-lotus-absolute\/","three_page_clicks":717,"three_page_impressions":29010},{"three_page_keys":"https:\/\/essentialoilwizardry.com\/product\/mugwort-essential-oil\/","three_page_clicks":139,"three_page_impressions":7830},{"three_page_keys":"https:\/\/essentialoilwizardry.com\/product\/tobacco-absolute\/","three_page_clicks":126,"three_page_impressions":6093},{"three_page_keys":"https:\/\/essentialoilwizardry.com\/product\/calea-z-aztec-dream-herb\/","three_page_clicks":111,"three_page_impressions":7097},{"three_page_keys":"https:\/\/essentialoilwizardry.com\/essential-oils\/","three_page_clicks":110,"three_page_impressions":3440},{"three_page_keys":"https:\/\/essentialoilwizardry.com\/product\/kava-extract-co2\/","three_page_clicks":109,"three_page_impressions":8084},{"three_page_keys":"https:\/\/essentialoilwizardry.com\/product\/dragons-blood-sangre-de-grado\/","three_page_clicks":100,"three_page_impressions":6148},{"three_page_keys":"https:\/\/essentialoilwizardry.com\/product\/trinity-blend\/","three_page_clicks":89,"three_page_impressions":3927},{"three_page_keys":"https:\/\/essentialoilwizardry.com\/product\/oil-of-gold\/","three_page_clicks":87,"three_page_impressions":998}],"six_page_array":[{"six_page_keys":"https:\/\/essentialoilwizardry.com\/","six_page_clicks":3305,"six_page_impressions":138738},{"six_page_keys":"https:\/\/essentialoilwizardry.com\/product\/blue-lotus-absolute\/","six_page_clicks":1384,"six_page_impressions":55322},{"six_page_keys":"https:\/\/essentialoilwizardry.com\/product\/mugwort-essential-oil\/","six_page_clicks":288,"six_page_impressions":14754},{"six_page_keys":"https:\/\/essentialoilwizardry.com\/product\/calea-z-aztec-dream-herb\/","six_page_clicks":271,"six_page_impressions":19452},{"six_page_keys":"https:\/\/essentialoilwizardry.com\/essential-oils\/","six_page_clicks":223,"six_page_impressions":6723},{"six_page_keys":"https:\/\/essentialoilwizardry.com\/product\/tobacco-absolute\/","six_page_clicks":214,"six_page_impressions":9469},{"six_page_keys":"https:\/\/essentialoilwizardry.com\/product\/kava-extract-co2\/","six_page_clicks":206,"six_page_impressions":23941},{"six_page_keys":"https:\/\/essentialoilwizardry.com\/product\/white-sage-essential-oil\/","six_page_clicks":188,"six_page_impressions":23574},{"six_page_keys":"https:\/\/essentialoilwizardry.com\/product\/dragons-blood-sangre-de-grado\/","six_page_clicks":185,"six_page_impressions":11804},{"six_page_keys":"https:\/\/essentialoilwizardry.com\/product\/ultrasonic-epimedium-horny-goat-weed-tincture\/","six_page_clicks":178,"six_page_impressions":21504}],"nine_page_array":[{"nine_page_keys":"https:\/\/essentialoilwizardry.com\/","nine_page_clicks":4999,"nine_page_impressions":154353},{"nine_page_keys":"https:\/\/essentialoilwizardry.com\/product\/blue-lotus-absolute\/","nine_page_clicks":1672,"nine_page_impressions":66899},{"nine_page_keys":"https:\/\/essentialoilwizardry.com\/essential-oils\/","nine_page_clicks":304,"nine_page_impressions":9265},{"nine_page_keys":"https:\/\/essentialoilwizardry.com\/product\/mugwort-essential-oil\/","nine_page_clicks":301,"nine_page_impressions":15533},{"nine_page_keys":"https:\/\/essentialoilwizardry.com\/product\/calea-z-aztec-dream-herb\/","nine_page_clicks":295,"nine_page_impressions":20227},{"nine_page_keys":"https:\/\/essentialoilwizardry.com\/product\/kava-extract-co2\/","nine_page_clicks":270,"nine_page_impressions":27786},{"nine_page_keys":"https:\/\/essentialoilwizardry.com\/product\/lilac-tincture\/","nine_page_clicks":269,"nine_page_impressions":4378},{"nine_page_keys":"https:\/\/essentialoilwizardry.com\/product\/tobacco-absolute\/","nine_page_clicks":225,"nine_page_impressions":10082},{"nine_page_keys":"https:\/\/essentialoilwizardry.com\/product\/white-sage-essential-oil\/","nine_page_clicks":218,"nine_page_impressions":27270},{"nine_page_keys":"https:\/\/essentialoilwizardry.com\/product\/dragons-blood-sangre-de-grado\/","nine_page_clicks":203,"nine_page_impressions":13558}],"year_page_array":[{"year_page_keys":"https:\/\/essentialoilwizardry.com\/","year_page_clicks":7166,"year_page_impressions":164306},{"year_page_keys":"https:\/\/essentialoilwizardry.com\/product\/blue-lotus-absolute\/","year_page_clicks":2040,"year_page_impressions":78006},{"year_page_keys":"https:\/\/essentialoilwizardry.com\/essential-oils\/","year_page_clicks":413,"year_page_impressions":12486},{"year_page_keys":"https:\/\/essentialoilwizardry.com\/product\/calea-z-aztec-dream-herb\/","year_page_clicks":323,"year_page_impressions":21033},{"year_page_keys":"https:\/\/essentialoilwizardry.com\/product\/kava-extract-co2\/","year_page_clicks":318,"year_page_impressions":30339},{"year_page_keys":"https:\/\/essentialoilwizardry.com\/product\/mugwort-essential-oil\/","year_page_clicks":316,"year_page_impressions":16222},{"year_page_keys":"https:\/\/essentialoilwizardry.com\/product\/kakanga-root\/","year_page_clicks":306,"year_page_impressions":1951},{"year_page_keys":"https:\/\/essentialoilwizardry.com\/product\/lilac-tincture\/","year_page_clicks":299,"year_page_impressions":4757},{"year_page_keys":"https:\/\/essentialoilwizardry.com\/product\/white-sage-essential-oil\/","year_page_clicks":262,"year_page_impressions":31045},{"year_page_keys":"https:\/\/essentialoilwizardry.com\/product\/oil-of-gold\/","year_page_clicks":238,"year_page_impressions":3068}],"two_year_page_array":[{"two_year_page_keys":"https:\/\/essentialoilwizardry.com\/","two_year_page_clicks":11033,"two_year_page_impressions":182179},{"two_year_page_keys":"https:\/\/essentialoilwizardry.com\/product\/blue-lotus-absolute\/","two_year_page_clicks":3455,"two_year_page_impressions":109816},{"two_year_page_keys":"https:\/\/essentialoilwizardry.com\/product\/mugwort-essential-oil\/","two_year_page_clicks":779,"two_year_page_impressions":29134},{"two_year_page_keys":"https:\/\/essentialoilwizardry.com\/essential-oils\/","two_year_page_clicks":596,"two_year_page_impressions":18722},{"two_year_page_keys":"https:\/\/essentialoilwizardry.com\/product\/white-sage-essential-oil\/","two_year_page_clicks":542,"two_year_page_impressions":50457},{"two_year_page_keys":"https:\/\/essentialoilwizardry.com\/product\/kava-extract-co2\/","two_year_page_clicks":537,"two_year_page_impressions":39559},{"two_year_page_keys":"https:\/\/essentialoilwizardry.com\/product\/kakanga-root\/","two_year_page_clicks":510,"two_year_page_impressions":2926},{"two_year_page_keys":"https:\/\/essentialoilwizardry.com\/product\/calea-z-aztec-dream-herb\/","two_year_page_clicks":469,"two_year_page_impressions":26667},{"two_year_page_keys":"https:\/\/essentialoilwizardry.com\/product\/dragons-blood-sangre-de-grado\/","two_year_page_clicks":422,"two_year_page_impressions":23414},{"two_year_page_keys":"https:\/\/essentialoilwizardry.com\/product\/ylang-ylang-essential-oil\/","two_year_page_clicks":392,"two_year_page_impressions":28198}]}