{"month_query_array":[{"month_query_keys":"fam solutions","month_query_clicks":66,"month_query_impressions":259,"month_query_ctr":0.2548262548262548,"month_query_position":3.9922779922779923},{"month_query_keys":"monitor arm singapore","month_query_clicks":13,"month_query_impressions":726,"month_query_ctr":0.01790633608815427,"month_query_position":5.848484848484849},{"month_query_keys":"fam solutions pte ltd","month_query_clicks":11,"month_query_impressions":70,"month_query_ctr":0.15714285714285714,"month_query_position":1.157142857142857},{"month_query_keys":"fam solution","month_query_clicks":5,"month_query_impressions":26,"month_query_ctr":0.19230769230769232,"month_query_position":3.3076923076923075},{"month_query_keys":"phone booth singapore","month_query_clicks":5,"month_query_impressions":155,"month_query_ctr":0.03225806451612903,"month_query_position":5.748387096774193},{"month_query_keys":"soundproof booth singapore","month_query_clicks":5,"month_query_impressions":60,"month_query_ctr":0.08333333333333333,"month_query_position":1.65},{"month_query_keys":"soundproof pod singapore","month_query_clicks":4,"month_query_impressions":42,"month_query_ctr":0.09523809523809523,"month_query_position":3.761904761904762},{"month_query_keys":"flight monitor arm","month_query_clicks":3,"month_query_impressions":77,"month_query_ctr":0.03896103896103896,"month_query_position":5.6103896103896105},{"month_query_keys":"monitor arms singapore","month_query_clicks":3,"month_query_impressions":66,"month_query_ctr":0.045454545454545456,"month_query_position":4.454545454545455},{"month_query_keys":"best monitor arm singapore","month_query_clicks":2,"month_query_impressions":72,"month_query_ctr":0.027777777777777776,"month_query_position":8.11111111111111}],"three_query_array":[{"three_query_keys":"fam solutions","three_query_clicks":186,"three_query_impressions":911,"three_query_ctr":0.20417124039517015,"three_query_position":5.585071350164654},{"three_query_keys":"monitor arm singapore","three_query_clicks":82,"three_query_impressions":1981,"three_query_ctr":0.04139323573952549,"three_query_position":4.985865724381625},{"three_query_keys":"soundproof booth singapore","three_query_clicks":30,"three_query_impressions":219,"three_query_ctr":0.136986301369863,"three_query_position":1.4703196347031964},{"three_query_keys":"fam solutions pte ltd","three_query_clicks":29,"three_query_impressions":226,"three_query_ctr":0.12831858407079647,"three_query_position":1.1283185840707965},{"three_query_keys":"monitor arm","three_query_clicks":29,"three_query_impressions":4629,"three_query_ctr":0.006264852019874703,"three_query_position":11.002160293799957},{"three_query_keys":"fam solution","three_query_clicks":24,"three_query_impressions":77,"three_query_ctr":0.3116883116883117,"three_query_position":3.1298701298701297},{"three_query_keys":"flight monitor arm","three_query_clicks":19,"three_query_impressions":197,"three_query_ctr":0.09644670050761421,"three_query_position":5.096446700507614},{"three_query_keys":"phone booth singapore","three_query_clicks":18,"three_query_impressions":400,"three_query_ctr":0.045,"three_query_position":5.12},{"three_query_keys":"keyboard tray singapore","three_query_clicks":16,"three_query_impressions":294,"three_query_ctr":0.05442176870748299,"three_query_position":4.659863945578231},{"three_query_keys":"monitor arms singapore","three_query_clicks":16,"three_query_impressions":188,"three_query_ctr":0.0851063829787234,"three_query_position":4.48936170212766}],"six_query_array":[{"six_query_keys":"fam solutions","six_query_clicks":314,"six_query_impressions":1443,"six_query_ctr":0.2176022176022176,"six_query_position":5.568260568260568},{"six_query_keys":"monitor arm singapore","six_query_clicks":124,"six_query_impressions":3201,"six_query_ctr":0.0387378944079975,"six_query_position":5.415495157763199},{"six_query_keys":"fam solutions pte ltd","six_query_clicks":51,"six_query_impressions":456,"six_query_ctr":0.1118421052631579,"six_query_position":1.1140350877192982},{"six_query_keys":"soundproof booth singapore","six_query_clicks":47,"six_query_impressions":317,"six_query_ctr":0.14826498422712933,"six_query_position":1.6593059936908516},{"six_query_keys":"phone booth singapore","six_query_clicks":41,"six_query_impressions":796,"six_query_ctr":0.05150753768844221,"six_query_position":4.894472361809045},{"six_query_keys":"keyboard tray singapore","six_query_clicks":39,"six_query_impressions":521,"six_query_ctr":0.07485604606525911,"six_query_position":3.2284069097888675},{"six_query_keys":"fam solution","six_query_clicks":38,"six_query_impressions":160,"six_query_ctr":0.2375,"six_query_position":3.64375},{"six_query_keys":"monitor arm","six_query_clicks":35,"six_query_impressions":6158,"six_query_ctr":0.005683663527119195,"six_query_position":11.409873335498538},{"six_query_keys":"flight monitor arm","six_query_clicks":25,"six_query_impressions":298,"six_query_ctr":0.08389261744966443,"six_query_position":4.691275167785235},{"six_query_keys":"flight tm","six_query_clicks":23,"six_query_impressions":206,"six_query_ctr":0.11165048543689321,"six_query_position":5.106796116504855}],"nine_query_array":[{"nine_query_keys":"fam solutions","nine_query_clicks":479,"nine_query_impressions":2148,"nine_query_ctr":0.22299813780260708,"nine_query_position":5.468342644320298},{"nine_query_keys":"monitor arm singapore","nine_query_clicks":154,"nine_query_impressions":4520,"nine_query_ctr":0.034070796460176994,"nine_query_position":5.847566371681416},{"nine_query_keys":"fam solutions pte ltd","nine_query_clicks":83,"nine_query_impressions":722,"nine_query_ctr":0.1149584487534626,"nine_query_position":1.1191135734072022},{"nine_query_keys":"keyboard tray singapore","nine_query_clicks":74,"nine_query_impressions":807,"nine_query_ctr":0.09169764560099132,"nine_query_position":2.6059479553903344},{"nine_query_keys":"soundproof booth singapore","nine_query_clicks":57,"nine_query_impressions":440,"nine_query_ctr":0.12954545454545455,"nine_query_position":1.9272727272727272},{"nine_query_keys":"phone booth singapore","nine_query_clicks":55,"nine_query_impressions":1231,"nine_query_ctr":0.04467912266450041,"nine_query_position":4.653127538586515},{"nine_query_keys":"fam solution","nine_query_clicks":53,"nine_query_impressions":236,"nine_query_ctr":0.2245762711864407,"nine_query_position":3.614406779661017},{"nine_query_keys":"flight tm","nine_query_clicks":37,"nine_query_impressions":308,"nine_query_ctr":0.12012987012987013,"nine_query_position":4.834415584415584},{"nine_query_keys":"monitor arm","nine_query_clicks":37,"nine_query_impressions":6588,"nine_query_ctr":0.005616272009714633,"nine_query_position":11.767304189435338},{"nine_query_keys":"flight monitor arm","nine_query_clicks":35,"nine_query_impressions":508,"nine_query_ctr":0.0688976377952756,"nine_query_position":4.350393700787402}],"one_year_query_array":[{"one_year_query_keys":"fam solutions","one_year_query_clicks":658,"one_year_query_impressions":3206,"one_year_query_ctr":0.2052401746724891,"one_year_query_position":5.906425452276981},{"one_year_query_keys":"monitor arm singapore","one_year_query_clicks":180,"one_year_query_impressions":5878,"one_year_query_ctr":0.030622660768969037,"one_year_query_position":6.190541000340252},{"one_year_query_keys":"fam solutions pte ltd","one_year_query_clicks":140,"one_year_query_impressions":891,"one_year_query_ctr":0.15712682379349047,"one_year_query_position":1.3232323232323233},{"one_year_query_keys":"keyboard tray singapore","one_year_query_clicks":98,"one_year_query_impressions":1052,"one_year_query_ctr":0.09315589353612168,"one_year_query_position":2.450570342205323},{"one_year_query_keys":"phone booth singapore","one_year_query_clicks":74,"one_year_query_impressions":1443,"one_year_query_ctr":0.05128205128205128,"one_year_query_position":4.537768537768538},{"one_year_query_keys":"fam solution","one_year_query_clicks":71,"one_year_query_impressions":325,"one_year_query_ctr":0.21846153846153846,"one_year_query_position":3.9507692307692306},{"one_year_query_keys":"soundproof booth singapore","one_year_query_clicks":61,"one_year_query_impressions":460,"one_year_query_ctr":0.13260869565217392,"one_year_query_position":2.302173913043478},{"one_year_query_keys":"flight monitor arm","one_year_query_clicks":51,"one_year_query_impressions":699,"one_year_query_ctr":0.07296137339055794,"one_year_query_position":3.9756795422031472},{"one_year_query_keys":"monitor arm","one_year_query_clicks":40,"one_year_query_impressions":7109,"one_year_query_ctr":0.0056266704177802785,"one_year_query_position":12.026586017724012},{"one_year_query_keys":"flight tm","one_year_query_clicks":38,"one_year_query_impressions":343,"one_year_query_ctr":0.11078717201166181,"one_year_query_position":4.868804664723032}],"two_year_query_array":[{"query_keys":"fam solutions","query_clicks":792,"query_impressions":3824,"query_ctr":0.20711297071129708,"query_position":5.927039748953975},{"query_keys":"monitor arm singapore","query_clicks":240,"query_impressions":7545,"query_ctr":0.03180914512922465,"query_position":6.832736911862161},{"query_keys":"fam solutions pte ltd","query_clicks":181,"query_impressions":1041,"query_ctr":0.17387127761767532,"query_position":1.5139289145052834},{"query_keys":"keyboard tray singapore","query_clicks":165,"query_impressions":1457,"query_ctr":0.11324639670555937,"query_position":2.2958133150308857},{"query_keys":"fam solution","query_clicks":83,"query_impressions":405,"query_ctr":0.20493827160493827,"query_position":4.148148148148149},{"query_keys":"phone booth singapore","query_clicks":80,"query_impressions":1752,"query_ctr":0.045662100456621,"query_position":6.958904109589041},{"query_keys":"standing desk converter singapore","query_clicks":78,"query_impressions":1823,"query_ctr":0.04278661546900713,"query_position":9.006034009873835},{"query_keys":"flight monitor arm","query_clicks":75,"query_impressions":853,"query_ctr":0.08792497069167643,"query_position":4.132473622508792},{"query_keys":"foldable table singapore","query_clicks":74,"query_impressions":4376,"query_ctr":0.016910420475319928,"query_position":17.48697440585009},{"query_keys":"height adjustable table singapore","query_clicks":72,"query_impressions":2917,"query_ctr":0.024682893383613302,"query_position":12.399040109701748}]}