{"current_six_sm_array":{"six_current_sm_location":["google \/ organic","(direct) \/ (none)","google \/ cpc","m.facebook.com \/ referral","l.facebook.com \/ referral","instagram.com \/ referral","prepatl.com \/ referral","prep.kitchen \/ referral","bing \/ organic","yelp.com \/ referral","austin.eater.com \/ referral","l.instagram.com \/ referral","duckduckgo \/ organic","lm.facebook.com \/ referral","complextime.com \/ referral","m.yelp.com \/ referral","yahoo \/ organic","adclays.com \/ referral","austin.culturemap.com \/ referral","commercialkitchenforrent.com \/ referral","naturallyaustin.org \/ referral","pickyourown.org \/ referral","prepatx.net \/ referral","residencestyle.com \/ referral","Facebook \/ cpc","app.asana.com \/ referral","app.convertri.com \/ referral","app.pipe.com \/ referral","aquilacommercial.com \/ referral","austin360.com \/ referral","austinchronicle.com \/ referral","austonia.com \/ referral","baidu \/ organic","beverlyhillsmagazine.com \/ referral","business.google.com \/ referral","businesscutter.com \/ referral","businesspartnermagazine.com \/ referral","businesstimenow.com \/ referral","cafe-madrid.com \/ referral","chamberofcommerce.com \/ referral","cherishsisters.com \/ referral","ciaopittsburgh.com \/ referral","cleantechloops.com \/ referral","cylex.us.com \/ referral","dilligant.com \/ referral","discoveringatx.com \/ referral","dnserrorassist.att.net \/ referral","ecosia.org \/ organic","entrepreneursbreak.com \/ referral","evokingminds.com \/ referral","experiencenissanleaf.com \/ referral","facebook.com \/ referral","foodarticles.net \/ referral","freesitemapgenerator.com \/ referral","gadgetflazz.com \/ referral","gembells.com \/ referral","goodthing2.com \/ referral","houseaffection.com \/ referral","housesumo.com \/ referral","hoverphenix.com \/ referral","howard-bison.com \/ referral","imark.agencydashboard.io \/ referral","info.dwt.com \/ referral","insightssuccess.com \/ referral","krafitis.com \/ referral","linkcentre.com \/ referral","littlebyties.com \/ referral","magazinemodule.com \/ referral","magazinestime.com \/ referral","mail.google.com \/ referral","maps.apple.com \/ referral","mckinsey.com \/ referral","myventurepad.com \/ referral","newscarter.com \/ referral","newsnblogs.com \/ referral","newyorkspaces.com \/ referral","oipinio.com \/ referral","pantheonuk.org \/ referral","patch.com \/ referral","publicistpaper.com \/ referral","reachlocal \/ cpc","roadrunner.lightning.force.com \/ referral","search.brave.com \/ referral","sso.lightning.force.com \/ referral","startpage.com \/ referral","statesman.com \/ referral","stylebes.com \/ referral","tastefulspace.com \/ referral","techduffer.com \/ referral","thebraggingmommy.com \/ referral","theimprints.agency \/ referral","therindtx.com \/ referral","thetotalentrepreneurs.com \/ referral","translate.google.com \/ referral","tribeza.com \/ referral","twlo.lightning.force.com \/ referral","tycoonstory.com \/ referral","urbanmatter.com \/ referral","usc-excel.officeapps.live.com \/ referral","wbsofts.com \/ referral","whatutalkingboutwillis.com \/ referral","wheon.com \/ referral","yandex.ru \/ referral"],"six_current_sm_goal":["274","162","119","80","21","16","13","11","5","5","4","4","3","3","2","2","2","1","1","1","1","1","1","1","0","0","0","0","0","0","0","0","0","0","0","0","0","0","0","0","0","0","0","0","0","0","0","0","0","0","0","0","0","0","0","0","0","0","0","0","0","0","0","0","0","0","0","0","0","0","0","0","0","0","0","0","0","0","0","0","0","0","0","0","0","0","0","0","0","0","0","0","0","0","0","0","0","0","0","0","0","0","0"]},"prev_six_sm_array":{"six_prev_sm_location":["tagassistant.google.com \/ referral","google \/ organic","(direct) \/ (none)","Austonia Daily Newsletter \/ email","Facebook \/ cpc","Texas-Boxed CPG Newsletter \/ email","Texas-Squared Startup Newsletter \/ email","adclays.com \/ referral","ampproject.org \/ referral","app.convertri.com \/ referral","app.glueup.com \/ referral","app.pipe.com \/ referral","app.vts.com \/ referral","aquilacommercial.com \/ referral","articleify.com \/ referral","austin-eater-com.cdn.ampproject.org \/ referral","austin.culturemap.com \/ referral","austin.eater.com \/ referral","austinchronicle.com \/ referral","austonia-com.cdn.ampproject.org \/ referral","austonia.com \/ referral","baidu \/ organic","beverlyhillsmagazine.com \/ referral","beyondvela.com \/ referral","bing \/ organic","business.google.com \/ referral","businessmodulehub.com \/ referral","businesspartnermagazine.com \/ referral","buzrush.com \/ referral","celluloidfun.com \/ referral","cherishsisters.com \/ referral","commercialkitchenforrent.com \/ referral","cupertinotimes.com \/ referral","discoveringatx.com \/ referral","duckduckgo \/ organic","ecosia.org \/ organic","elmens.com \/ referral","entrepreneursbreak.com \/ referral","europeanbusinessreview.com \/ referral","facebook.com \/ referral","farm2austin.my.stacker.app \/ referral","feedly.com \/ referral","feedyweedy.com \/ referral","flipboard.com \/ referral","gadgetflazz.com \/ referral","getpocket.com \/ referral","google \/ cpc","hammburg.com \/ referral","homoq.com \/ referral","houseaffection.com \/ referral","imark.agencydashboard.io \/ referral","insightssuccess.com \/ referral","insta.tel \/ referral","instagram.com \/ referral","krafitis.com \/ referral","kxan.com \/ referral","l.alpha.facebook.com \/ referral","l.facebook.com \/ referral","l.instagram.com \/ referral","lebenn.com \/ referral","linkauthority.com \/ referral","linkedin.com \/ referral","linkin.bio \/ social","lm.facebook.com \/ referral","loopnet.com \/ referral","lostvirtualtour.com \/ referral","lunchboxtech.lightning.force.com \/ referral","m.facebook.com \/ referral","m.yelp.com \/ referral","magazinesweekly.com \/ referral","mail.google.com \/ referral","mail.yahoo.com \/ referral","maps.apple.com \/ referral","mo-track.org \/ referral","mszgnews.com \/ referral","mydecorative.com \/ referral","myventurepad.com \/ referral","naturallyaustin.org \/ referral","newsbreak.com \/ referral","ops.picrights.com \/ referral","outsidetheboxmom.com \/ referral","pickyourown.org \/ referral","poshbeautyblog.com \/ referral","prep.kitchen \/ referral","prepatl.com \/ referral","prepatx.net \/ referral","reactor.leadforensics.com \/ referral","realitypaper.com \/ referral","residencestyle.com \/ referral","revoada.net \/ referral","salessystem.logicalposition.com \/ referral","sfo.redirect.systems \/ referral","smartnews.com \/ referral","so.com \/ organic","sogou \/ organic","t.co \/ referral","tastefulspace.com \/ referral","techonpc.com \/ referral","techsprohub.com \/ referral","theedgesearch.com \/ referral","thehall.net \/ referral","theimprints.agency \/ referral","thepostcity.com \/ referral","therindtx.com \/ referral","thewowdecor.com \/ referral","thewowstyle.com \/ referral","trello.com \/ referral","tribeza.com \/ referral","tuffsocial.com \/ referral","tycoonstory.com \/ referral","upwork.com \/ referral","urbanmatter-com.cdn.ampproject.org \/ referral","urbanmatter.com \/ referral","us.search.yahoo.com \/ referral","ventsmagazine.com \/ referral","voxmedia.stories.usechorus.com \/ referral","wanderglobe.org \/ referral","webflow.com \/ referral","webmobistar.com \/ referral","wheon.com \/ referral","wholepost.com \/ referral","www-kxan-com.cdn.ampproject.org \/ referral","yahoo \/ organic","yelp.com \/ referral"],"six_prev_sm_goal":["3","2","0","0","0","0","0","0","0","0","0","0","0","0","0","0","0","0","0","0","0","0","0","0","0","0","0","0","0","0","0","0","0","0","0","0","0","0","0","0","0","0","0","0","0","0","0","0","0","0","0","0","0","0","0","0","0","0","0","0","0","0","0","0","0","0","0","0","0","0","0","0","0","0","0","0","0","0","0","0","0","0","0","0","0","0","0","0","0","0","0","0","0","0","0","0","0","0","0","0","0","0","0","0","0","0","0","0","0","0","0","0","0","0","0","0","0","0","0","0","0","0","0","0"]},"current_six_sm_organic_array":{"six_current_organic_sm_location":["bing \/ organic","duckduckgo \/ organic","google \/ organic","yahoo \/ organic"],"six_current_organic_sm_goal":["5","3","274","2"]},"prev_six_sm_organic_array":{"six_prev_organic_sm_location":["google \/ organic"],"six_prev_organic_sm_goal":["2"]}}