{"month_query_array":[{"month_query_keys":"gutter mesh direct","month_query_clicks":2,"month_query_impressions":4,"month_query_ctr":0.5,"month_query_position":1},{"month_query_keys":"fascia and guttering suppliers near me","month_query_clicks":1,"month_query_impressions":1,"month_query_ctr":1,"month_query_position":1},{"month_query_keys":"gutter guard kit","month_query_clicks":1,"month_query_impressions":25,"month_query_ctr":0.04,"month_query_position":33.96},{"month_query_keys":"gutter mesh australia","month_query_clicks":1,"month_query_impressions":23,"month_query_ctr":0.043478260869565216,"month_query_position":8.826086956521738},{"month_query_keys":"gutter protector","month_query_clicks":1,"month_query_impressions":63,"month_query_ctr":0.015873015873015872,"month_query_position":59.93650793650794},{"month_query_keys":"stick on gutter guard","month_query_clicks":1,"month_query_impressions":17,"month_query_ctr":0.058823529411764705,"month_query_position":10.823529411764707},{"month_query_keys":"aluminum gutter guard","month_query_clicks":0,"month_query_impressions":5,"month_query_ctr":0,"month_query_position":93.8},{"month_query_keys":"best diy gutter guard","month_query_clicks":0,"month_query_impressions":1,"month_query_ctr":0,"month_query_position":79},{"month_query_keys":"best diy gutter guards","month_query_clicks":0,"month_query_impressions":2,"month_query_ctr":0,"month_query_position":87},{"month_query_keys":"best gutter guard","month_query_clicks":0,"month_query_impressions":10,"month_query_ctr":0,"month_query_position":91.6}],"three_query_array":[{"three_query_keys":"gutter mesh direct","three_query_clicks":16,"three_query_impressions":40,"three_query_ctr":0.4,"three_query_position":1.15},{"three_query_keys":"gutter mesh","three_query_clicks":13,"three_query_impressions":1571,"three_query_ctr":0.008274984086569064,"three_query_position":15.275620623806493},{"three_query_keys":"gutter guard direct","three_query_clicks":9,"three_query_impressions":546,"three_query_ctr":0.016483516483516484,"three_query_position":6.913919413919414},{"three_query_keys":"gutter mesh australia","three_query_clicks":4,"three_query_impressions":72,"three_query_ctr":0.05555555555555555,"three_query_position":8.86111111111111},{"three_query_keys":"guttermesh","three_query_clicks":4,"three_query_impressions":317,"three_query_ctr":0.012618296529968454,"three_query_position":4.832807570977918},{"three_query_keys":"stick on gutter guard","three_query_clicks":3,"three_query_impressions":48,"three_query_ctr":0.0625,"three_query_position":9.770833333333334},{"three_query_keys":"aluminium gutter guard","three_query_clicks":1,"three_query_impressions":2,"three_query_ctr":0.5,"three_query_position":3.5},{"three_query_keys":"fascia and guttering suppliers near me","three_query_clicks":1,"three_query_impressions":1,"three_query_ctr":1,"three_query_position":1},{"three_query_keys":"guaranteed gutter protection","three_query_clicks":1,"three_query_impressions":68,"three_query_ctr":0.014705882352941176,"three_query_position":8.029411764705882},{"three_query_keys":"gutter guard kit","three_query_clicks":1,"three_query_impressions":79,"three_query_ctr":0.012658227848101266,"three_query_position":30.79746835443038}],"six_query_array":[{"six_query_keys":"gutter mesh","six_query_clicks":35,"six_query_impressions":3543,"six_query_ctr":0.009878633926051369,"six_query_position":15.116285633643805},{"six_query_keys":"gutter mesh direct","six_query_clicks":31,"six_query_impressions":95,"six_query_ctr":0.3263157894736842,"six_query_position":1.168421052631579},{"six_query_keys":"gutter guard direct","six_query_clicks":18,"six_query_impressions":1037,"six_query_ctr":0.017357762777242044,"six_query_position":7.295081967213115},{"six_query_keys":"guttermesh","six_query_clicks":10,"six_query_impressions":608,"six_query_ctr":0.01644736842105263,"six_query_position":5.996710526315789},{"six_query_keys":"gutter mesh australia","six_query_clicks":9,"six_query_impressions":150,"six_query_ctr":0.06,"six_query_position":8.506666666666668},{"six_query_keys":"gutter guard","six_query_clicks":4,"six_query_impressions":1076,"six_query_ctr":0.0037174721189591076,"six_query_position":82.94052044609666},{"six_query_keys":"stick on gutter guard","six_query_clicks":4,"six_query_impressions":86,"six_query_ctr":0.046511627906976744,"six_query_position":13.662790697674419},{"six_query_keys":"gutter guard australia","six_query_clicks":2,"six_query_impressions":521,"six_query_ctr":0.003838771593090211,"six_query_position":23.595009596928982},{"six_query_keys":"aluminium gutter guard","six_query_clicks":1,"six_query_impressions":17,"six_query_ctr":0.058823529411764705,"six_query_position":14.352941176470589},{"six_query_keys":"fascia and guttering suppliers near me","six_query_clicks":1,"six_query_impressions":1,"six_query_ctr":1,"six_query_position":1}],"nine_query_array":[{"nine_query_keys":"gutter mesh direct","nine_query_clicks":55,"nine_query_impressions":156,"nine_query_ctr":0.3525641025641026,"nine_query_position":1.25},{"nine_query_keys":"gutter mesh","nine_query_clicks":43,"nine_query_impressions":4854,"nine_query_ctr":0.008858673259167697,"nine_query_position":16.455912649361352},{"nine_query_keys":"gutter guard direct","nine_query_clicks":20,"nine_query_impressions":1376,"nine_query_ctr":0.014534883720930232,"nine_query_position":7.565406976744186},{"nine_query_keys":"gutter mesh australia","nine_query_clicks":12,"nine_query_impressions":228,"nine_query_ctr":0.05263157894736842,"nine_query_position":8.074561403508772},{"nine_query_keys":"guttermesh","nine_query_clicks":12,"nine_query_impressions":864,"nine_query_ctr":0.013888888888888888,"nine_query_position":6.780092592592593},{"nine_query_keys":"gutter guard","nine_query_clicks":6,"nine_query_impressions":2229,"nine_query_ctr":0.0026917900403768506,"nine_query_position":77.76132794975325},{"nine_query_keys":"stick on gutter guard","nine_query_clicks":4,"nine_query_impressions":86,"nine_query_ctr":0.046511627906976744,"nine_query_position":13.662790697674419},{"nine_query_keys":"gutter guard australia","nine_query_clicks":3,"nine_query_impressions":813,"nine_query_ctr":0.0036900369003690036,"nine_query_position":22.394833948339482},{"nine_query_keys":"gutter guard installation near me","nine_query_clicks":2,"nine_query_impressions":13,"nine_query_ctr":0.15384615384615385,"nine_query_position":16.53846153846154},{"nine_query_keys":"gutter guard mesh","nine_query_clicks":2,"nine_query_impressions":1608,"nine_query_ctr":0.0012437810945273632,"nine_query_position":25.251243781094526}],"one_year_query_array":[{"one_year_query_keys":"gutter mesh","one_year_query_clicks":66,"one_year_query_impressions":7504,"one_year_query_ctr":0.008795309168443496,"one_year_query_position":16.10261194029851},{"one_year_query_keys":"gutter mesh direct","one_year_query_clicks":65,"one_year_query_impressions":178,"one_year_query_ctr":0.3651685393258427,"one_year_query_position":1.247191011235955},{"one_year_query_keys":"gutter guard direct","one_year_query_clicks":23,"one_year_query_impressions":1650,"one_year_query_ctr":0.013939393939393939,"one_year_query_position":7.464848484848485},{"one_year_query_keys":"guttermesh","one_year_query_clicks":15,"one_year_query_impressions":1110,"one_year_query_ctr":0.013513513513513514,"one_year_query_position":6.976576576576576},{"one_year_query_keys":"gutter mesh australia","one_year_query_clicks":12,"one_year_query_impressions":279,"one_year_query_ctr":0.043010752688172046,"one_year_query_position":7.584229390681004},{"one_year_query_keys":"gutter guard","one_year_query_clicks":7,"one_year_query_impressions":4360,"one_year_query_ctr":0.0016055045871559634,"one_year_query_position":67.8552752293578},{"one_year_query_keys":"gutter guard australia","one_year_query_clicks":7,"one_year_query_impressions":1116,"one_year_query_ctr":0.0062724014336917565,"one_year_query_position":20.831541218637994},{"one_year_query_keys":"stick on gutter guard","one_year_query_clicks":4,"one_year_query_impressions":86,"one_year_query_ctr":0.046511627906976744,"one_year_query_position":13.662790697674419},{"one_year_query_keys":"diy gutter guard","one_year_query_clicks":2,"one_year_query_impressions":724,"one_year_query_ctr":0.0027624309392265192,"one_year_query_position":42.30939226519337},{"one_year_query_keys":"gutter guard installation near me","one_year_query_clicks":2,"one_year_query_impressions":13,"one_year_query_ctr":0.15384615384615385,"one_year_query_position":16.53846153846154}],"two_year_query_array":[{"query_keys":"gutter mesh direct","query_clicks":74,"query_impressions":202,"query_ctr":0.36633663366336633,"query_position":1.2178217821782178},{"query_keys":"gutter mesh","query_clicks":66,"query_impressions":8057,"query_ctr":0.008191634603450416,"query_position":15.905051508005462},{"query_keys":"gutter guard direct","query_clicks":23,"query_impressions":1732,"query_ctr":0.013279445727482679,"query_position":7.4607390300230945},{"query_keys":"guttermesh","query_clicks":15,"query_impressions":1181,"query_ctr":0.012701100762066046,"query_position":7.3175275190516516},{"query_keys":"gutter mesh australia","query_clicks":12,"query_impressions":299,"query_ctr":0.04013377926421405,"query_position":7.535117056856187},{"query_keys":"gutter guard","query_clicks":7,"query_impressions":4360,"query_ctr":0.0016055045871559634,"query_position":67.8552752293578},{"query_keys":"gutter guard australia","query_clicks":7,"query_impressions":1200,"query_ctr":0.005833333333333334,"query_position":22.503333333333334},{"query_keys":"stick on gutter guard","query_clicks":4,"query_impressions":86,"query_ctr":0.046511627906976744,"query_position":13.662790697674419},{"query_keys":"diy gutter guard","query_clicks":2,"query_impressions":782,"query_ctr":0.0025575447570332483,"query_position":44.171355498721226},{"query_keys":"gutter guard installation near me","query_clicks":2,"query_impressions":13,"query_ctr":0.15384615384615385,"query_position":16.53846153846154}]}