[{"country":"usa","clicks":18,"impressions":1047,"ctr":0.017191977077363897,"position":71.58357211079274},{"country":"ind","clicks":7,"impressions":307,"ctr":0.02280130293159609,"position":100.0456026058632},{"country":"can","clicks":3,"impressions":53,"ctr":0.05660377358490566,"position":78.20754716981132},{"country":"phl","clicks":2,"impressions":93,"ctr":0.021505376344086023,"position":76.76344086021506},{"country":"aus","clicks":1,"impressions":45,"ctr":0.022222222222222223,"position":56.44444444444444},{"country":"bgd","clicks":1,"impressions":75,"ctr":0.013333333333333334,"position":112.21333333333334},{"country":"swe","clicks":1,"impressions":31,"ctr":0.03225806451612903,"position":67.41935483870968},{"country":"tur","clicks":1,"impressions":222,"ctr":0.0045045045045045045,"position":108.54954954954955},{"country":"afg","clicks":0,"impressions":3,"ctr":0,"position":172.66666666666666},{"country":"ago","clicks":0,"impressions":2,"ctr":0,"position":94.5},{"country":"alb","clicks":0,"impressions":9,"ctr":0,"position":140.33333333333334},{"country":"are","clicks":0,"impressions":16,"ctr":0,"position":94.4375},{"country":"arg","clicks":0,"impressions":185,"ctr":0,"position":98.58378378378379},{"country":"arm","clicks":0,"impressions":5,"ctr":0,"position":71},{"country":"aut","clicks":0,"impressions":7,"ctr":0,"position":73.14285714285714},{"country":"aze","clicks":0,"impressions":8,"ctr":0,"position":110.5},{"country":"bdi","clicks":0,"impressions":1,"ctr":0,"position":54},{"country":"bel","clicks":0,"impressions":5,"ctr":0,"position":98.8},{"country":"ben","clicks":0,"impressions":2,"ctr":0,"position":136.5},{"country":"bgr","clicks":0,"impressions":14,"ctr":0,"position":79.57142857142857},{"country":"bhr","clicks":0,"impressions":1,"ctr":0,"position":38},{"country":"bhs","clicks":0,"impressions":2,"ctr":0,"position":84.5},{"country":"bih","clicks":0,"impressions":9,"ctr":0,"position":132.55555555555554},{"country":"blr","clicks":0,"impressions":6,"ctr":0,"position":111.16666666666667},{"country":"bmu","clicks":0,"impressions":1,"ctr":0,"position":95},{"country":"bol","clicks":0,"impressions":24,"ctr":0,"position":137.54166666666666},{"country":"bra","clicks":0,"impressions":289,"ctr":0,"position":94.93425605536332},{"country":"brb","clicks":0,"impressions":1,"ctr":0,"position":54},{"country":"bwa","clicks":0,"impressions":3,"ctr":0,"position":171.66666666666666},{"country":"che","clicks":0,"impressions":5,"ctr":0,"position":113.2},{"country":"chl","clicks":0,"impressions":22,"ctr":0,"position":105.72727272727273},{"country":"chn","clicks":0,"impressions":2,"ctr":0,"position":103.5},{"country":"civ","clicks":0,"impressions":6,"ctr":0,"position":153.66666666666666},{"country":"cmr","clicks":0,"impressions":1,"ctr":0,"position":172},{"country":"cod","clicks":0,"impressions":3,"ctr":0,"position":137},{"country":"cog","clicks":0,"impressions":1,"ctr":0,"position":96},{"country":"col","clicks":0,"impressions":94,"ctr":0,"position":101.30851063829788},{"country":"cpv","clicks":0,"impressions":4,"ctr":0,"position":147.5},{"country":"cri","clicks":0,"impressions":3,"ctr":0,"position":110.66666666666667},{"country":"cyp","clicks":0,"impressions":8,"ctr":0,"position":123.25},{"country":"cze","clicks":0,"impressions":25,"ctr":0,"position":90.48},{"country":"deu","clicks":0,"impressions":53,"ctr":0,"position":72.05660377358491},{"country":"dnk","clicks":0,"impressions":4,"ctr":0,"position":84.5},{"country":"dom","clicks":0,"impressions":39,"ctr":0,"position":122.17948717948718},{"country":"dza","clicks":0,"impressions":53,"ctr":0,"position":114.75471698113208},{"country":"ecu","clicks":0,"impressions":34,"ctr":0,"position":129.02941176470588},{"country":"egy","clicks":0,"impressions":90,"ctr":0,"position":104.91111111111111},{"country":"esp","clicks":0,"impressions":63,"ctr":0,"position":81.03174603174604},{"country":"eth","clicks":0,"impressions":4,"ctr":0,"position":55.25},{"country":"fin","clicks":0,"impressions":7,"ctr":0,"position":95.28571428571429},{"country":"fra","clicks":0,"impressions":36,"ctr":0,"position":74.69444444444444},{"country":"gab","clicks":0,"impressions":1,"ctr":0,"position":174},{"country":"gbr","clicks":0,"impressions":169,"ctr":0,"position":58.06508875739645},{"country":"geo","clicks":0,"impressions":6,"ctr":0,"position":96},{"country":"gha","clicks":0,"impressions":26,"ctr":0,"position":136.34615384615384},{"country":"grc","clicks":0,"impressions":9,"ctr":0,"position":107.77777777777777},{"country":"grd","clicks":0,"impressions":1,"ctr":0,"position":48},{"country":"gtm","clicks":0,"impressions":17,"ctr":0,"position":144.23529411764707},{"country":"guf","clicks":0,"impressions":1,"ctr":0,"position":50},{"country":"guy","clicks":0,"impressions":2,"ctr":0,"position":88},{"country":"hkg","clicks":0,"impressions":19,"ctr":0,"position":98.94736842105263},{"country":"hnd","clicks":0,"impressions":8,"ctr":0,"position":139.25},{"country":"hrv","clicks":0,"impressions":3,"ctr":0,"position":114.66666666666667},{"country":"hti","clicks":0,"impressions":3,"ctr":0,"position":125},{"country":"hun","clicks":0,"impressions":20,"ctr":0,"position":93.15},{"country":"idn","clicks":0,"impressions":246,"ctr":0,"position":119.32520325203252},{"country":"irl","clicks":0,"impressions":1,"ctr":0,"position":94},{"country":"irn","clicks":0,"impressions":23,"ctr":0,"position":110.43478260869566},{"country":"irq","clicks":0,"impressions":37,"ctr":0,"position":114.45945945945945},{"country":"isl","clicks":0,"impressions":2,"ctr":0,"position":90},{"country":"isr","clicks":0,"impressions":23,"ctr":0,"position":108},{"country":"ita","clicks":0,"impressions":49,"ctr":0,"position":92.04081632653062},{"country":"jam","clicks":0,"impressions":5,"ctr":0,"position":89.8},{"country":"jor","clicks":0,"impressions":11,"ctr":0,"position":103.27272727272727},{"country":"jpn","clicks":0,"impressions":48,"ctr":0,"position":101.52083333333333},{"country":"kaz","clicks":0,"impressions":11,"ctr":0,"position":113.81818181818181},{"country":"ken","clicks":0,"impressions":28,"ctr":0,"position":136.57142857142858},{"country":"kgz","clicks":0,"impressions":3,"ctr":0,"position":54.333333333333336},{"country":"khm","clicks":0,"impressions":13,"ctr":0,"position":124.15384615384616},{"country":"kor","clicks":0,"impressions":182,"ctr":0,"position":78.17032967032966},{"country":"kwt","clicks":0,"impressions":1,"ctr":0,"position":63},{"country":"lao","clicks":0,"impressions":3,"ctr":0,"position":113.33333333333333},{"country":"lbn","clicks":0,"impressions":6,"ctr":0,"position":138.66666666666666},{"country":"lby","clicks":0,"impressions":12,"ctr":0,"position":113.75},{"country":"lka","clicks":0,"impressions":14,"ctr":0,"position":110.57142857142857},{"country":"ltu","clicks":0,"impressions":16,"ctr":0,"position":67.3125},{"country":"lux","clicks":0,"impressions":1,"ctr":0,"position":100},{"country":"lva","clicks":0,"impressions":8,"ctr":0,"position":76.125},{"country":"mac","clicks":0,"impressions":2,"ctr":0,"position":34.5},{"country":"mar","clicks":0,"impressions":34,"ctr":0,"position":124.23529411764706},{"country":"mda","clicks":0,"impressions":9,"ctr":0,"position":87},{"country":"mex","clicks":0,"impressions":103,"ctr":0,"position":100.52427184466019},{"country":"mkd","clicks":0,"impressions":18,"ctr":0,"position":141},{"country":"mli","clicks":0,"impressions":1,"ctr":0,"position":35},{"country":"mmr","clicks":0,"impressions":9,"ctr":0,"position":137.77777777777777},{"country":"mng","clicks":0,"impressions":5,"ctr":0,"position":107},{"country":"moz","clicks":0,"impressions":1,"ctr":0,"position":45},{"country":"mrt","clicks":0,"impressions":1,"ctr":0,"position":100},{"country":"mtq","clicks":0,"impressions":1,"ctr":0,"position":100},{"country":"mus","clicks":0,"impressions":1,"ctr":0,"position":50}]