{"month_country_array":[{"month_country_keys":"usa","month_country_clicks":295,"month_country_impressions":2680,"month_country_ctr":0.11007462686567164,"month_country_position":35.01194029850746},{"month_country_keys":"aus","month_country_clicks":1,"month_country_impressions":73,"month_country_ctr":0.0136986301369863,"month_country_position":47.9041095890411},{"month_country_keys":"can","month_country_clicks":1,"month_country_impressions":163,"month_country_ctr":0.006134969325153374,"month_country_position":41.214723926380366},{"month_country_keys":"gbr","month_country_clicks":1,"month_country_impressions":300,"month_country_ctr":0.0033333333333333335,"month_country_position":58.376666666666665},{"month_country_keys":"grc","month_country_clicks":1,"month_country_impressions":10,"month_country_ctr":0.1,"month_country_position":47.6},{"month_country_keys":"isr","month_country_clicks":1,"month_country_impressions":17,"month_country_ctr":0.058823529411764705,"month_country_position":48.470588235294116},{"month_country_keys":"afg","month_country_clicks":0,"month_country_impressions":5,"month_country_ctr":0,"month_country_position":48.2},{"month_country_keys":"ago","month_country_clicks":0,"month_country_impressions":3,"month_country_ctr":0,"month_country_position":75},{"month_country_keys":"alb","month_country_clicks":0,"month_country_impressions":10,"month_country_ctr":0,"month_country_position":58.8},{"month_country_keys":"are","month_country_clicks":0,"month_country_impressions":14,"month_country_ctr":0,"month_country_position":55.142857142857146}],"three_country_array":[{"threeCountry_keys":"usa","threeCountry_clicks":977,"threeCountry_impressions":9267,"threeCountry_ctr":0.10542786230711125,"threeCountry_position":33.290277328153664},{"threeCountry_keys":"can","threeCountry_clicks":6,"threeCountry_impressions":520,"threeCountry_ctr":0.011538461538461539,"threeCountry_position":41.271153846153844},{"threeCountry_keys":"aus","threeCountry_clicks":3,"threeCountry_impressions":248,"threeCountry_ctr":0.012096774193548387,"threeCountry_position":49.80241935483871},{"threeCountry_keys":"gbr","threeCountry_clicks":2,"threeCountry_impressions":737,"threeCountry_ctr":0.0027137042062415195,"threeCountry_position":57.66078697421981},{"threeCountry_keys":"and","threeCountry_clicks":1,"threeCountry_impressions":7,"threeCountry_ctr":0.14285714285714285,"threeCountry_position":11.571428571428571},{"threeCountry_keys":"bra","threeCountry_clicks":1,"threeCountry_impressions":945,"threeCountry_ctr":0.0010582010582010583,"threeCountry_position":65.10793650793651},{"threeCountry_keys":"brb","threeCountry_clicks":1,"threeCountry_impressions":20,"threeCountry_ctr":0.05,"threeCountry_position":56.9},{"threeCountry_keys":"fra","threeCountry_clicks":1,"threeCountry_impressions":228,"threeCountry_ctr":0.0043859649122807015,"threeCountry_position":55.85964912280702},{"threeCountry_keys":"grc","threeCountry_clicks":1,"threeCountry_impressions":40,"threeCountry_ctr":0.025,"threeCountry_position":63.025},{"threeCountry_keys":"hnd","threeCountry_clicks":1,"threeCountry_impressions":30,"threeCountry_ctr":0.03333333333333333,"threeCountry_position":54.733333333333334}],"six_country_array":[{"six_month_Country_keys":"usa","six_month_Country_clicks":1178,"six_month_Country_impressions":10973,"six_month_Country_ctr":0.10735441538321334,"six_month_Country_position":32.566845894468244},{"six_month_Country_keys":"can","six_month_Country_clicks":6,"six_month_Country_impressions":613,"six_month_Country_ctr":0.009787928221859706,"six_month_Country_position":40.01794453507341},{"six_month_Country_keys":"aus","six_month_Country_clicks":4,"six_month_Country_impressions":279,"six_month_Country_ctr":0.014336917562724014,"six_month_Country_position":50.37275985663082},{"six_month_Country_keys":"gbr","six_month_Country_clicks":2,"six_month_Country_impressions":881,"six_month_Country_ctr":0.0022701475595913734,"six_month_Country_position":57.38592508513053},{"six_month_Country_keys":"and","six_month_Country_clicks":1,"six_month_Country_impressions":7,"six_month_Country_ctr":0.14285714285714285,"six_month_Country_position":11.571428571428571},{"six_month_Country_keys":"bra","six_month_Country_clicks":1,"six_month_Country_impressions":1129,"six_month_Country_ctr":0.0008857395925597874,"six_month_Country_position":65.15677590788309},{"six_month_Country_keys":"brb","six_month_Country_clicks":1,"six_month_Country_impressions":24,"six_month_Country_ctr":0.041666666666666664,"six_month_Country_position":61.5},{"six_month_Country_keys":"fra","six_month_Country_clicks":1,"six_month_Country_impressions":272,"six_month_Country_ctr":0.003676470588235294,"six_month_Country_position":56.0110294117647},{"six_month_Country_keys":"grc","six_month_Country_clicks":1,"six_month_Country_impressions":45,"six_month_Country_ctr":0.022222222222222223,"six_month_Country_position":63.48888888888889},{"six_month_Country_keys":"hnd","six_month_Country_clicks":1,"six_month_Country_impressions":30,"six_month_Country_ctr":0.03333333333333333,"six_month_Country_position":54.733333333333334}],"nine_country_array":[{"nine_month_Country_keys":"usa","nine_month_Country_clicks":1178,"nine_month_Country_impressions":10973,"nine_month_Country_ctr":0.10735441538321334,"nine_month_Country_position":32.566845894468244},{"nine_month_Country_keys":"can","nine_month_Country_clicks":6,"nine_month_Country_impressions":613,"nine_month_Country_ctr":0.009787928221859706,"nine_month_Country_position":40.01794453507341},{"nine_month_Country_keys":"aus","nine_month_Country_clicks":4,"nine_month_Country_impressions":279,"nine_month_Country_ctr":0.014336917562724014,"nine_month_Country_position":50.37275985663082},{"nine_month_Country_keys":"gbr","nine_month_Country_clicks":2,"nine_month_Country_impressions":881,"nine_month_Country_ctr":0.0022701475595913734,"nine_month_Country_position":57.38592508513053},{"nine_month_Country_keys":"and","nine_month_Country_clicks":1,"nine_month_Country_impressions":7,"nine_month_Country_ctr":0.14285714285714285,"nine_month_Country_position":11.571428571428571},{"nine_month_Country_keys":"bra","nine_month_Country_clicks":1,"nine_month_Country_impressions":1129,"nine_month_Country_ctr":0.0008857395925597874,"nine_month_Country_position":65.15677590788309},{"nine_month_Country_keys":"brb","nine_month_Country_clicks":1,"nine_month_Country_impressions":24,"nine_month_Country_ctr":0.041666666666666664,"nine_month_Country_position":61.5},{"nine_month_Country_keys":"fra","nine_month_Country_clicks":1,"nine_month_Country_impressions":272,"nine_month_Country_ctr":0.003676470588235294,"nine_month_Country_position":56.0110294117647},{"nine_month_Country_keys":"grc","nine_month_Country_clicks":1,"nine_month_Country_impressions":45,"nine_month_Country_ctr":0.022222222222222223,"nine_month_Country_position":63.48888888888889},{"nine_month_Country_keys":"hnd","nine_month_Country_clicks":1,"nine_month_Country_impressions":30,"nine_month_Country_ctr":0.03333333333333333,"nine_month_Country_position":54.733333333333334}],"year_country_array":[{"year_Country_keys":"usa","year_Country_clicks":1178,"year_Country_impressions":10973,"year_Country_ctr":0.10735441538321334,"year_Country_position":32.566845894468244},{"year_Country_keys":"can","year_Country_clicks":6,"year_Country_impressions":613,"year_Country_ctr":0.009787928221859706,"year_Country_position":40.01794453507341},{"year_Country_keys":"aus","year_Country_clicks":4,"year_Country_impressions":279,"year_Country_ctr":0.014336917562724014,"year_Country_position":50.37275985663082},{"year_Country_keys":"gbr","year_Country_clicks":2,"year_Country_impressions":881,"year_Country_ctr":0.0022701475595913734,"year_Country_position":57.38592508513053},{"year_Country_keys":"and","year_Country_clicks":1,"year_Country_impressions":7,"year_Country_ctr":0.14285714285714285,"year_Country_position":11.571428571428571},{"year_Country_keys":"bra","year_Country_clicks":1,"year_Country_impressions":1129,"year_Country_ctr":0.0008857395925597874,"year_Country_position":65.15677590788309},{"year_Country_keys":"brb","year_Country_clicks":1,"year_Country_impressions":24,"year_Country_ctr":0.041666666666666664,"year_Country_position":61.5},{"year_Country_keys":"fra","year_Country_clicks":1,"year_Country_impressions":272,"year_Country_ctr":0.003676470588235294,"year_Country_position":56.0110294117647},{"year_Country_keys":"grc","year_Country_clicks":1,"year_Country_impressions":45,"year_Country_ctr":0.022222222222222223,"year_Country_position":63.48888888888889},{"year_Country_keys":"hnd","year_Country_clicks":1,"year_Country_impressions":30,"year_Country_ctr":0.03333333333333333,"year_Country_position":54.733333333333334}],"two_year_country_array":[{"two_year_Country_keys":"usa","two_year_Country_clicks":1178,"two_year_Country_impressions":10973,"two_year_Country_ctr":0.10735441538321334,"two_year_Country_position":32.566845894468244},{"two_year_Country_keys":"can","two_year_Country_clicks":6,"two_year_Country_impressions":613,"two_year_Country_ctr":0.009787928221859706,"two_year_Country_position":40.01794453507341},{"two_year_Country_keys":"aus","two_year_Country_clicks":4,"two_year_Country_impressions":279,"two_year_Country_ctr":0.014336917562724014,"two_year_Country_position":50.37275985663082},{"two_year_Country_keys":"gbr","two_year_Country_clicks":2,"two_year_Country_impressions":881,"two_year_Country_ctr":0.0022701475595913734,"two_year_Country_position":57.38592508513053},{"two_year_Country_keys":"and","two_year_Country_clicks":1,"two_year_Country_impressions":7,"two_year_Country_ctr":0.14285714285714285,"two_year_Country_position":11.571428571428571},{"two_year_Country_keys":"bra","two_year_Country_clicks":1,"two_year_Country_impressions":1129,"two_year_Country_ctr":0.0008857395925597874,"two_year_Country_position":65.15677590788309},{"two_year_Country_keys":"brb","two_year_Country_clicks":1,"two_year_Country_impressions":24,"two_year_Country_ctr":0.041666666666666664,"two_year_Country_position":61.5},{"two_year_Country_keys":"fra","two_year_Country_clicks":1,"two_year_Country_impressions":272,"two_year_Country_ctr":0.003676470588235294,"two_year_Country_position":56.0110294117647},{"two_year_Country_keys":"grc","two_year_Country_clicks":1,"two_year_Country_impressions":45,"two_year_Country_ctr":0.022222222222222223,"two_year_Country_position":63.48888888888889},{"two_year_Country_keys":"hnd","two_year_Country_clicks":1,"two_year_Country_impressions":30,"two_year_Country_ctr":0.03333333333333333,"two_year_Country_position":54.733333333333334}]}