{"current_twoyear_sm_array":{"twoyear_current_sm_location":["(direct) \/ (none)","google \/ organic","adforms.citiservi.com \/ referral","admin.cioreview.com \/ referral","ahrefs.com \/ referral","aol \/ organic","app.asana.com \/ referral","app.joinhandshake.com \/ referral","aqvalit.com \/ referral","atcommons.com \/ referral","az1-ts5.a2hosting.com:2083 \/ referral","baidu \/ organic","basecamp.com \/ referral","benchmarkhs.com \/ referral","bing \/ organic","bize.admin.yelp.com \/ referral","block.opendns.com \/ referral","ca.search.yahoo.com \/ referral","circa.lightning.force.com \/ referral","clutch.co \/ referral","communityheroes.us \/ referral","cuisineeurope.com \/ referral","dileaders.com \/ referral","ditechdrivedownyourmortgage.com \/ referral","docs.google.com \/ referral","duckduckgo \/ organic","ecosia.org \/ organic","engine.presearch.org \/ referral","eqbsystems.com \/ referral","event.on24.com \/ referral","facebook.com \/ referral","fyple.com \/ referral","georgiambda.my.salesforce.com \/ referral","ggc.joinhandshake.com \/ referral","gsu.joinhandshake.com \/ referral","hilaryblog.top \/ referral","keyword.com \/ referral","l.facebook.com \/ referral","lafonpublishing.com \/ referral","linkauthority.com \/ referral","linkedin.com \/ referral","localbusinesslisting.org \/ referral","m.facebook.com \/ referral","naver.com \/ referral","rootviewnetworks.com \/ referral","salaryapac.lightning.force.com \/ referral","salescore.mediabrains.com \/ referral","so.com \/ organic","sogou \/ organic","statics.teams.cdn.office.net \/ referral","themanifest.com \/ referral","thetea.live \/ referral","translate.google.com \/ referral","tuugo.us \/ referral","upwork.com \/ referral","us.enrollbusiness.com \/ referral","vaptcha.com \/ referral","wiley-corp.lightning.force.com \/ referral","woodbridgegrp.lightning.force.com \/ referral","yahoo \/ organic","yelp.com \/ referral","zipleaf.us \/ referral","zoominfo.com \/ referral"],"twoyear_current_sm_goal":["10","8","0","0","0","0","0","0","0","0","0","0","0","0","0","0","0","0","0","0","0","0","0","0","0","0","0","0","0","0","0","0","0","0","0","0","0","0","0","0","0","0","0","0","0","0","0","0","0","0","0","0","0","0","0","0","0","0","0","0","0","0","0"]},"prev_twoyear_sm_array":{"twoyear_prev_sm_location":[],"twoyear_prev_sm_goal":[]},"current_twoyear_sm_organic_array":{"twoyear_current_organic_sm_location":["google \/ organic"],"twoyear_current_organic_sm_goal":["8"]},"prev_twoyear_sm_organic_array":{"twoyear_prev_organic_sm_location":[],"twoyear_prev_organic_sm_goal":[]}}