{"month_device_array":[{"month_device_keys":"DESKTOP","month_device_clicks":3,"month_device_impressions":1470,"month_device_ctr":0.0020408163265306124,"month_device_position":66.59659863945578},{"month_device_keys":"MOBILE","month_device_clicks":2,"month_device_impressions":425,"month_device_ctr":0.004705882352941176,"month_device_position":74.02352941176471},{"month_device_keys":"TABLET","month_device_clicks":0,"month_device_impressions":2,"month_device_ctr":0,"month_device_position":60}],"three_device_array":[{"three_device_keys":"DESKTOP","three_device_clicks":10,"three_device_impressions":5468,"three_device_ctr":0.0018288222384784199,"three_device_position":67.81986100950988},{"three_device_keys":"MOBILE","three_device_clicks":5,"three_device_impressions":1259,"three_device_ctr":0.003971405877680699,"three_device_position":75.39793486894361},{"three_device_keys":"TABLET","three_device_clicks":0,"three_device_impressions":5,"three_device_ctr":0,"three_device_position":52.2}],"six_device_array":[{"six_device_keys":"DESKTOP","six_device_clicks":28,"six_device_impressions":20120,"six_device_ctr":0.0013916500994035786,"six_device_position":66.02112326043738},{"six_device_keys":"MOBILE","six_device_clicks":7,"six_device_impressions":3856,"six_device_ctr":0.0018153526970954357,"six_device_position":70.46991701244814},{"six_device_keys":"TABLET","six_device_clicks":0,"six_device_impressions":64,"six_device_ctr":0,"six_device_position":54.90625}],"nine_device_array":[{"nine_device_keys":"DESKTOP","nine_device_clicks":51,"nine_device_impressions":33777,"nine_device_ctr":0.0015099031885602628,"nine_device_position":62.745152026526924},{"nine_device_keys":"MOBILE","nine_device_clicks":15,"nine_device_impressions":6316,"nine_device_ctr":0.0023749208359721344,"nine_device_position":66.41402786573781},{"nine_device_keys":"TABLET","nine_device_clicks":0,"nine_device_impressions":151,"nine_device_ctr":0,"nine_device_position":52.56953642384106}],"year_device_array":[{"year_device_keys":"DESKTOP","year_device_clicks":74,"year_device_impressions":46766,"year_device_ctr":0.0015823461489116025,"year_device_position":62.31345421887696},{"year_device_keys":"MOBILE","year_device_clicks":17,"year_device_impressions":8232,"year_device_ctr":0.00206511175898931,"year_device_position":65.35046161321671},{"year_device_keys":"TABLET","year_device_clicks":0,"year_device_impressions":203,"year_device_ctr":0,"year_device_position":54.251231527093594}],"two_year_device_array":[{"two_year_device_keys":"DESKTOP","two_year_device_clicks":101,"two_year_device_impressions":67171,"two_year_device_ctr":0.001503625076297807,"two_year_device_position":63.38153369757782},{"two_year_device_keys":"MOBILE","two_year_device_clicks":21,"two_year_device_impressions":11928,"two_year_device_ctr":0.0017605633802816902,"two_year_device_position":67.011569416499},{"two_year_device_keys":"TABLET","two_year_device_clicks":0,"two_year_device_impressions":264,"two_year_device_ctr":0,"two_year_device_position":52.10606060606061}]}