[{"queries":"domaine dardagny","clicks":11,"impressions":51,"ctr":0.21568627450980393,"position":4.921568627450981},{"queries":"domaine du centaure","clicks":3,"impressions":78,"ctr":0.038461538461538464,"position":19.858974358974358},{"queries":"regions in switzerland","clicks":3,"impressions":308,"ctr":0.00974025974025974,"position":9.957792207792208},{"queries":"les eliades","clicks":2,"impressions":20,"ctr":0.1,"position":7.1},{"queries":"dardagny","clicks":1,"impressions":71,"ctr":0.014084507042253521,"position":26.56338028169014},{"queries":"dardagny wine","clicks":1,"impressions":11,"ctr":0.09090909090909091,"position":3.8181818181818183},{"queries":"domaine centaure","clicks":1,"impressions":9,"ctr":0.1111111111111111,"position":41.666666666666664},{"queries":"domaine de centaure","clicks":1,"impressions":7,"ctr":0.14285714285714285,"position":15.428571428571429},{"queries":"du centaure","clicks":1,"impressions":1,"ctr":1,"position":2},{"queries":"gamaret","clicks":1,"impressions":59,"ctr":0.01694915254237288,"position":32.20338983050847},{"queries":"local guide program","clicks":1,"impressions":2,"ctr":0.5,"position":1},{"queries":"regions of switzerland","clicks":1,"impressions":768,"ctr":0.0013020833333333333,"position":10.11328125},{"queries":"wine importers california","clicks":1,"impressions":6,"ctr":0.16666666666666666,"position":81.83333333333333},{"queries":"zeus wine","clicks":1,"impressions":19,"ctr":0.05263157894736842,"position":12.526315789473685},{"queries":"26 cantons of switzerland","clicks":0,"impressions":4,"ctr":0,"position":27.25},{"queries":"52 ddi","clicks":0,"impressions":1,"ctr":0,"position":71},{"queries":"ades drink korea","clicks":0,"impressions":1,"ctr":0,"position":1},{"queries":"allobroges wine","clicks":0,"impressions":1,"ctr":0,"position":84},{"queries":"allwine","clicks":0,"impressions":1,"ctr":0,"position":91},{"queries":"allwine curry inc.","clicks":0,"impressions":2,"ctr":0,"position":46.5},{"queries":"areas in switzerland","clicks":0,"impressions":1,"ctr":0,"position":78},{"queries":"areas of switzerland","clicks":0,"impressions":11,"ctr":0,"position":14.272727272727273},{"queries":"bc swiss","clicks":0,"impressions":4,"ctr":0,"position":82.25},{"queries":"best swiss red wine","clicks":0,"impressions":2,"ctr":0,"position":73.5},{"queries":"best swiss wine producers","clicks":0,"impressions":3,"ctr":0,"position":39.666666666666664},{"queries":"best swiss wines","clicks":0,"impressions":2,"ctr":0,"position":66},{"queries":"bukettrebe","clicks":0,"impressions":1,"ctr":0,"position":59},{"queries":"california wine importers","clicks":0,"impressions":3,"ctr":0,"position":86},{"queries":"camay wine","clicks":0,"impressions":86,"ctr":0,"position":4.476744186046512},{"queries":"centaure","clicks":0,"impressions":81,"ctr":0,"position":53.18518518518518},{"queries":"centaure covid","clicks":0,"impressions":1,"ctr":0,"position":78},{"queries":"centuare","clicks":0,"impressions":4,"ctr":0,"position":10},{"queries":"chasselas","clicks":0,"impressions":274,"ctr":0,"position":47.667883211678834},{"queries":"chasselas de geneve","clicks":0,"impressions":2,"ctr":0,"position":17.5},{"queries":"chasselas swiss wine","clicks":0,"impressions":2,"ctr":0,"position":57},{"queries":"chasselas wine","clicks":0,"impressions":56,"ctr":0,"position":60.607142857142854},{"queries":"chasselas wine near me","clicks":0,"impressions":1,"ctr":0,"position":16},{"queries":"chasselas wines","clicks":0,"impressions":3,"ctr":0,"position":42},{"queries":"clos des pins dardagny","clicks":0,"impressions":1,"ctr":0,"position":65},{"queries":"club domaine","clicks":0,"impressions":4,"ctr":0,"position":13},{"queries":"club history switzerland","clicks":0,"impressions":1,"ctr":0,"position":57},{"queries":"contact ddi","clicks":0,"impressions":1,"ctr":0,"position":92},{"queries":"covid centaure","clicks":0,"impressions":1,"ctr":0,"position":84},{"queries":"cremant blanc","clicks":0,"impressions":1,"ctr":0,"position":24},{"queries":"cremant blanc de blanc","clicks":0,"impressions":1,"ctr":0,"position":10},{"queries":"cremant ros\u00e9","clicks":0,"impressions":52,"ctr":0,"position":75.5},{"queries":"cr\u00e9mant","clicks":0,"impressions":2,"ctr":0,"position":85},{"queries":"cr\u00e9mant de dardagny","clicks":0,"impressions":27,"ctr":0,"position":6.7407407407407405},{"queries":"cuisse de jupiter","clicks":0,"impressions":1,"ctr":0,"position":74},{"queries":"danaides","clicks":0,"impressions":18,"ctr":0,"position":67.05555555555556},{"queries":"dana\u00efdes","clicks":0,"impressions":7,"ctr":0,"position":55.42857142857143},{"queries":"dardagny suisse","clicks":0,"impressions":1,"ctr":0,"position":86},{"queries":"dardagny switzerland","clicks":0,"impressions":2,"ctr":0,"position":19.5},{"queries":"dardagny vin","clicks":0,"impressions":3,"ctr":0,"position":87.66666666666667},{"queries":"ddi 57","clicks":0,"impressions":1,"ctr":0,"position":57},{"queries":"ddi 800","clicks":0,"impressions":3,"ctr":0,"position":81},{"queries":"ddi california","clicks":0,"impressions":9,"ctr":0,"position":41.44444444444444},{"queries":"dezeus","clicks":0,"impressions":3,"ctr":0,"position":29.333333333333332},{"queries":"dillon stine","clicks":0,"impressions":65,"ctr":0,"position":20.692307692307693},{"queries":"domaine a pinot noir","clicks":0,"impressions":8,"ctr":0,"position":56.5},{"queries":"domaine ca","clicks":0,"impressions":1,"ctr":0,"position":66},{"queries":"domaine club","clicks":0,"impressions":4,"ctr":0,"position":52.75},{"queries":"domaine de zeus","clicks":0,"impressions":21,"ctr":0,"position":43.714285714285715},{"queries":"domaine des centaures","clicks":0,"impressions":4,"ctr":0,"position":66.25},{"queries":"domaine des hutins","clicks":0,"impressions":6,"ctr":0,"position":34.166666666666664},{"queries":"domaine di","clicks":0,"impressions":1,"ctr":0,"position":35},{"queries":"domaine du","clicks":0,"impressions":2,"ctr":0,"position":91.5},{"queries":"domaine du centaure dardagny","clicks":0,"impressions":9,"ctr":0,"position":10.444444444444445},{"queries":"domaine du have","clicks":0,"impressions":7,"ctr":0,"position":53.57142857142857},{"queries":"domaine du merlot","clicks":0,"impressions":1,"ctr":0,"position":71},{"queries":"domaine hutins","clicks":0,"impressions":1,"ctr":0,"position":4},{"queries":"domaine le centaure","clicks":0,"impressions":4,"ctr":0,"position":26.25},{"queries":"domaine les hutins","clicks":0,"impressions":29,"ctr":0,"position":29.20689655172414},{"queries":"domaine nightclub","clicks":0,"impressions":2,"ctr":0,"position":95.5},{"queries":"domaine nom","clicks":0,"impressions":7,"ctr":0,"position":63.42857142857143},{"queries":"domaine pinot noir","clicks":0,"impressions":3,"ctr":0,"position":35},{"queries":"domaine red wine","clicks":0,"impressions":2,"ctr":0,"position":26},{"queries":"domaine white wine","clicks":0,"impressions":1,"ctr":0,"position":33},{"queries":"domaine wine","clicks":0,"impressions":48,"ctr":0,"position":82.875},{"queries":"dylan stine","clicks":0,"impressions":16,"ctr":0,"position":16.5625},{"queries":"eastern switzerland wines","clicks":0,"impressions":16,"ctr":0,"position":72.4375},{"queries":"edmond pruning","clicks":0,"impressions":34,"ctr":0,"position":84.79411764705883},{"queries":"edmond winery","clicks":0,"impressions":4,"ctr":0,"position":82.5},{"queries":"elaides","clicks":0,"impressions":1,"ctr":0,"position":82},{"queries":"eliades","clicks":0,"impressions":10,"ctr":0,"position":71.5},{"queries":"findling","clicks":0,"impressions":2,"ctr":0,"position":49},{"queries":"findling inc","clicks":0,"impressions":6,"ctr":0,"position":21.5},{"queries":"gamaret garanoir","clicks":0,"impressions":33,"ctr":0,"position":38.42424242424242},{"queries":"gamaret wine","clicks":0,"impressions":8,"ctr":0,"position":25.25},{"queries":"gamay delivery","clicks":0,"impressions":4,"ctr":0,"position":91.5},{"queries":"gamay delivery near me","clicks":0,"impressions":3,"ctr":0,"position":79.66666666666667},{"queries":"garanoir","clicks":0,"impressions":80,"ctr":0,"position":48.025},{"queries":"garanoir wine","clicks":0,"impressions":2,"ctr":0,"position":15.5},{"queries":"garavor","clicks":0,"impressions":1,"ctr":0,"position":2},{"queries":"geneva wine region","clicks":0,"impressions":13,"ctr":0,"position":63.61538461538461},{"queries":"gen\u00e8ve wines","clicks":0,"impressions":2,"ctr":0,"position":90.5},{"queries":"german region of switzerland","clicks":0,"impressions":1,"ctr":0,"position":1},{"queries":"gewurtzraminer","clicks":0,"impressions":4,"ctr":0,"position":87.25},{"queries":"graub\u00fcnden wine region","clicks":0,"impressions":27,"ctr":0,"position":86.22222222222223},{"queries":"history of phylloxera","clicks":0,"impressions":24,"ctr":0,"position":58.666666666666664}]