{"month_page_array":[{"month_page_keys":"https:\/\/www.scubadeep.com\/","month_page_clicks":67,"month_page_impressions":3135},{"month_page_keys":"https:\/\/scubadeep.com\/th\/","month_page_clicks":15,"month_page_impressions":330},{"month_page_keys":"https:\/\/www.scubadeep.com\/service\/open-water-course-phuket\/","month_page_clicks":4,"month_page_impressions":617},{"month_page_keys":"https:\/\/www.scubadeep.com\/scuba-diving\/","month_page_clicks":3,"month_page_impressions":31},{"month_page_keys":"https:\/\/www.scubadeep.com\/padi-courses\/","month_page_clicks":2,"month_page_impressions":113},{"month_page_keys":"https:\/\/www.scubadeep.com\/scubathailand01\/","month_page_clicks":2,"month_page_impressions":2},{"month_page_keys":"https:\/\/scubadeep.com\/fr\/","month_page_clicks":1,"month_page_impressions":48},{"month_page_keys":"https:\/\/scubadeep.com\/fr\/service\/phi-phi-islands-scuba-diving\/","month_page_clicks":1,"month_page_impressions":25},{"month_page_keys":"https:\/\/scubadeep.com\/th\/3395b06aea090a645d7361efcd9768f6-2\/","month_page_clicks":1,"month_page_impressions":21},{"month_page_keys":"https:\/\/scubadeep.com\/th\/3395b06aea090a645d7361efcd9768f6\/","month_page_clicks":1,"month_page_impressions":4}],"three_page_array":[{"three_page_keys":"https:\/\/www.scubadeep.com\/","three_page_clicks":133,"three_page_impressions":4118},{"three_page_keys":"https:\/\/scubadeep.com\/th\/","three_page_clicks":19,"three_page_impressions":443},{"three_page_keys":"https:\/\/www.scubadeep.com\/service\/open-water-course-phuket\/","three_page_clicks":4,"three_page_impressions":619},{"three_page_keys":"https:\/\/www.scubadeep.com\/scuba-diving\/","three_page_clicks":3,"three_page_impressions":38},{"three_page_keys":"https:\/\/scubadeep.com\/scuba-diving\/","three_page_clicks":2,"three_page_impressions":41},{"three_page_keys":"https:\/\/scubadeep.com\/th\/boat_schedule\/boat-schedule-2\/","three_page_clicks":2,"three_page_impressions":10},{"three_page_keys":"https:\/\/scubadeep.com\/th\/boat_schedule\/boat-schedule\/","three_page_clicks":2,"three_page_impressions":3},{"three_page_keys":"https:\/\/scubadeep.com\/th\/service\/discover-scuba-diving\/","three_page_clicks":2,"three_page_impressions":21},{"three_page_keys":"https:\/\/scubadeep.com\/th\/service\/fun-dive\/","three_page_clicks":2,"three_page_impressions":31},{"three_page_keys":"https:\/\/www.scubadeep.com\/padi-courses\/","three_page_clicks":2,"three_page_impressions":190}],"six_page_array":[{"six_page_keys":"https:\/\/www.scubadeep.com\/","six_page_clicks":133,"six_page_impressions":4160},{"six_page_keys":"https:\/\/scubadeep.com\/th\/","six_page_clicks":19,"six_page_impressions":443},{"six_page_keys":"https:\/\/www.scubadeep.com\/service\/open-water-course-phuket\/","six_page_clicks":4,"six_page_impressions":619},{"six_page_keys":"https:\/\/www.scubadeep.com\/scuba-diving\/","six_page_clicks":3,"six_page_impressions":38},{"six_page_keys":"https:\/\/scubadeep.com\/scuba-diving\/","six_page_clicks":2,"six_page_impressions":41},{"six_page_keys":"https:\/\/scubadeep.com\/th\/boat_schedule\/boat-schedule-2\/","six_page_clicks":2,"six_page_impressions":10},{"six_page_keys":"https:\/\/scubadeep.com\/th\/boat_schedule\/boat-schedule\/","six_page_clicks":2,"six_page_impressions":3},{"six_page_keys":"https:\/\/scubadeep.com\/th\/service\/discover-scuba-diving\/","six_page_clicks":2,"six_page_impressions":21},{"six_page_keys":"https:\/\/scubadeep.com\/th\/service\/fun-dive\/","six_page_clicks":2,"six_page_impressions":31},{"six_page_keys":"https:\/\/www.scubadeep.com\/padi-courses\/","six_page_clicks":2,"six_page_impressions":190}],"nine_page_array":[{"nine_page_keys":"https:\/\/www.scubadeep.com\/","nine_page_clicks":133,"nine_page_impressions":4160},{"nine_page_keys":"https:\/\/scubadeep.com\/th\/","nine_page_clicks":19,"nine_page_impressions":443},{"nine_page_keys":"https:\/\/www.scubadeep.com\/service\/open-water-course-phuket\/","nine_page_clicks":4,"nine_page_impressions":619},{"nine_page_keys":"https:\/\/www.scubadeep.com\/scuba-diving\/","nine_page_clicks":3,"nine_page_impressions":38},{"nine_page_keys":"https:\/\/scubadeep.com\/scuba-diving\/","nine_page_clicks":2,"nine_page_impressions":41},{"nine_page_keys":"https:\/\/scubadeep.com\/th\/boat_schedule\/boat-schedule-2\/","nine_page_clicks":2,"nine_page_impressions":10},{"nine_page_keys":"https:\/\/scubadeep.com\/th\/boat_schedule\/boat-schedule\/","nine_page_clicks":2,"nine_page_impressions":3},{"nine_page_keys":"https:\/\/scubadeep.com\/th\/service\/discover-scuba-diving\/","nine_page_clicks":2,"nine_page_impressions":21},{"nine_page_keys":"https:\/\/scubadeep.com\/th\/service\/fun-dive\/","nine_page_clicks":2,"nine_page_impressions":31},{"nine_page_keys":"https:\/\/www.scubadeep.com\/padi-courses\/","nine_page_clicks":2,"nine_page_impressions":190}],"year_page_array":[{"year_page_keys":"https:\/\/www.scubadeep.com\/","year_page_clicks":133,"year_page_impressions":4160},{"year_page_keys":"https:\/\/scubadeep.com\/th\/","year_page_clicks":19,"year_page_impressions":443},{"year_page_keys":"https:\/\/www.scubadeep.com\/service\/open-water-course-phuket\/","year_page_clicks":4,"year_page_impressions":619},{"year_page_keys":"https:\/\/www.scubadeep.com\/scuba-diving\/","year_page_clicks":3,"year_page_impressions":38},{"year_page_keys":"https:\/\/scubadeep.com\/scuba-diving\/","year_page_clicks":2,"year_page_impressions":41},{"year_page_keys":"https:\/\/scubadeep.com\/th\/boat_schedule\/boat-schedule-2\/","year_page_clicks":2,"year_page_impressions":10},{"year_page_keys":"https:\/\/scubadeep.com\/th\/boat_schedule\/boat-schedule\/","year_page_clicks":2,"year_page_impressions":3},{"year_page_keys":"https:\/\/scubadeep.com\/th\/service\/discover-scuba-diving\/","year_page_clicks":2,"year_page_impressions":21},{"year_page_keys":"https:\/\/scubadeep.com\/th\/service\/fun-dive\/","year_page_clicks":2,"year_page_impressions":31},{"year_page_keys":"https:\/\/www.scubadeep.com\/padi-courses\/","year_page_clicks":2,"year_page_impressions":190}],"two_year_page_array":[{"two_year_page_keys":"https:\/\/www.scubadeep.com\/","two_year_page_clicks":133,"two_year_page_impressions":4160},{"two_year_page_keys":"https:\/\/scubadeep.com\/th\/","two_year_page_clicks":19,"two_year_page_impressions":443},{"two_year_page_keys":"https:\/\/www.scubadeep.com\/service\/open-water-course-phuket\/","two_year_page_clicks":4,"two_year_page_impressions":619},{"two_year_page_keys":"https:\/\/www.scubadeep.com\/scuba-diving\/","two_year_page_clicks":3,"two_year_page_impressions":38},{"two_year_page_keys":"https:\/\/scubadeep.com\/scuba-diving\/","two_year_page_clicks":2,"two_year_page_impressions":41},{"two_year_page_keys":"https:\/\/scubadeep.com\/th\/boat_schedule\/boat-schedule-2\/","two_year_page_clicks":2,"two_year_page_impressions":10},{"two_year_page_keys":"https:\/\/scubadeep.com\/th\/boat_schedule\/boat-schedule\/","two_year_page_clicks":2,"two_year_page_impressions":3},{"two_year_page_keys":"https:\/\/scubadeep.com\/th\/service\/discover-scuba-diving\/","two_year_page_clicks":2,"two_year_page_impressions":21},{"two_year_page_keys":"https:\/\/scubadeep.com\/th\/service\/fun-dive\/","two_year_page_clicks":2,"two_year_page_impressions":31},{"two_year_page_keys":"https:\/\/www.scubadeep.com\/padi-courses\/","two_year_page_clicks":2,"two_year_page_impressions":190}]}